pythonaoe2/__init__.py
pythonaoe2/aoe2.py
pythonaoe2-0.2.5.dist-info/LICENSE
pythonaoe2-0.2.5.dist-info/METADATA
pythonaoe2-0.2.5.dist-info/WHEEL
pythonaoe2-0.2.5.dist-info/top_level.txt
pythonaoe2-0.2.5.dist-info/RECORD
