Metadata-Version: 2.1
Name: pythonaoe2
Version: 0.2.5
Summary: Using Python to interact with the AOE2 API
Home-page: https://github.com/L-E-iT/python-aoe2
Author: Brian Elliott
License: MIT
Project-URL: Bug Tracker, https://github.com/L-E-iT/python-aoe2/issues
Platform: UNKNOWN
License-File: LICENSE
Requires-Dist: requests
